mkdocs_plugins/__init__.py
mkdocs_plugins/task_collector.py
mkdocs_task_collector-0.1.14.dist-info/LICENSE
mkdocs_task_collector-0.1.14.dist-info/METADATA
mkdocs_task_collector-0.1.14.dist-info/WHEEL
mkdocs_task_collector-0.1.14.dist-info/entry_points.txt
mkdocs_task_collector-0.1.14.dist-info/top_level.txt
mkdocs_task_collector-0.1.14.dist-info/RECORD
