Metadata-Version: 2.1
Name: mkdocs-task-collector
Version: 0.1.14
Summary: A MkDocs plugin to collect TODO, NOTE, and PLACEHOLDER annotations.
Home-page: https://github.com/costantinoai/mkdocs-task-collector
Author: Andrea Costantino
Author-email: andreaivancostantino@outlook.it
Project-URL: Bug Reports, https://github.com/costantinoai/mkdocs-task-collector/issues
Project-URL: Source, https://github.com/costantinoai/mkdocs-task-collector
Keywords: mkdocs plugin task todo note placeholder
Classifier: Development Status :: 4 - Beta
Classifier: Environment :: Plugins
Classifier: Intended Audience :: Developers
Classifier: License :: OSI Approved :: MIT License
Classifier: Operating System :: OS Independent
Classifier: Programming Language :: Python
Classifier: Programming Language :: Python :: 3
Classifier: Programming Language :: Python :: 3 :: Only
Classifier: Programming Language :: Python :: 3.6
Classifier: Programming Language :: Python :: 3.7
Classifier: Programming Language :: Python :: 3.8
Classifier: Programming Language :: Python :: 3.9
Classifier: Programming Language :: Python :: 3.10
Classifier: Programming Language :: Python :: 3.11
Classifier: Topic :: Documentation
Classifier: Topic :: Software Development :: Documentation
Requires-Python: >=3.6
License-File: LICENSE
Requires-Dist: mkdocs >=1.1
